bref/__init__.py
bref/book.py
bref/canon.py
bref/ref.py
bref/reflist.py
bref/refparser.py
bref/refpat.py
bref/refrange.py
bref-0.6.0.dist-info/DESCRIPTION.rst
bref-0.6.0.dist-info/METADATA
bref-0.6.0.dist-info/RECORD
bref-0.6.0.dist-info/WHEEL
bref-0.6.0.dist-info/metadata.json
bref-0.6.0.dist-info/top_level.txt
