Metadata-Version: 2.0
Name: bref
Version: 0.6.0
Summary: Reference parsing and formatting library. Designed for Bible references, but can be used for any reference with 'Book ch:vs' or 'Book ch.vs' format, where ch and vs are numbers.
Home-page: https://github.com/BlackEarth/bref
Author: Sean Harrison
Author-email: sah@blackearthgroup.com
License: LGPL 3.0
Platform: UNKNOWN
Classifier: Development Status :: 4 - Beta
Classifier: Intended Audience :: Developers
Classifier: License :: OSI Approved :: GNU Library or Lesser General Public License (LGPL)
Classifier: Programming Language :: Python :: 3
Requires-Dist: bl
Requires-Dist: bxml
Provides-Extra: dev
Provides-Extra: test
